gibss/__init__.py
gibss/additive.py
gibss/conditional_normal_means.py
gibss/credible_sets.py
gibss/gd_backtracking.py
gibss/irsl.py
gibss/logistic.py
gibss/logistic2d.py
gibss/logistic_sparse.py
gibss/logisticprofile.py
gibss/newton.py
gibss/ser.py
gibss/utils.py
gibss-0.1.1.dist-info/METADATA
gibss-0.1.1.dist-info/WHEEL
gibss-0.1.1.dist-info/RECORD
