Metadata-Version: 2.4
Name: gibss
Version: 0.1.1
Summary: Add your description here
Requires-Python: >=3.11
Requires-Dist: jax>=0.4.38
Requires-Dist: jaxlib>=0.4.38
Requires-Dist: numpy>=2.2.2
Requires-Dist: scipy>=1.15.1
Requires-Dist: tqdm>=4.67.1
